nbtool/__init__.py
nbtool/core.py
nbtool/docker.py
nbtool/freeze.py
nbtool/project.py
nbtool/release.py
nbtool/resources/Dockerfile
nbtool/resources/python.tgz
nbtool-0.0.16.data/scripts/nb
nbtool-0.0.16.dist-info/LICENSE
nbtool-0.0.16.dist-info/METADATA
nbtool-0.0.16.dist-info/WHEEL
nbtool-0.0.16.dist-info/top_level.txt
nbtool-0.0.16.dist-info/RECORD
