Metadata-Version: 2.1
Name: nbtool
Version: 0.0.16
Summary: nb tool package
Home-page: UNKNOWN
Author: zhchangAuthor
Author-email: zhchang@gmail.com
License: UNKNOWN
Platform: UNKNOWN
Classifier: Programming Language :: Python :: 3
Classifier: License :: OSI Approved :: MIT License
Classifier: Operating System :: OS Independent
Requires-Python: >=3.4
